README.rst
setup.cfg
setup.py
resolve_target/__init__.py
resolve_target/resolve_target.py
resolve_target.egg-info/PKG-INFO
resolve_target.egg-info/SOURCES.txt
resolve_target.egg-info/dependency_links.txt
resolve_target.egg-info/entry_points.txt
resolve_target.egg-info/top_level.txt