Metadata-Version: 1.1
Name: resolve-target
Version: 1.0.0.post1
Summary: Contacts URL(s) and resolves the redirection target(s).
Home-page: https://github.com/avitebskiy/resolve_target
Author: Aleksey Vitebskiy
Author-email: aleksey.vitebskiy@gmail.com
License: MIT
Download-URL: https://github.com/avitebskiy/resolve_target/archive/1.0.0.tar.gz
Keywords: http,www,developer,redirect,web,hostname
Platform: UNKNOWN
Classifier: Development Status :: 5 - Production/Stable
Classifier: Intended Audience :: Developers
Classifier: Topic :: Software Development
Classifier: Topic :: Software Development :: Libraries :: Python Modules
Classifier: Topic :: Internet :: WWW/HTTP
Classifier: License :: OSI Approved :: MIT License
Classifier: Programming Language :: Python :: 2
Classifier: Programming Language :: Python :: 2.7
Classifier: Programming Language :: Python :: 3
Classifier: Programming Language :: Python :: 3.6
